[{"t":"pen","d":[162,164,162,164,162,164,164,167],"c":"rgba(0,0,0,1)","th":4,"username":"cGV0ZXI","drawId":0,"at":""},{"t":"pen","d":[162,164,162,164,164,167,168,172],"c":"rgba(0,0,0,1)","th":4,"username":"cGV0ZXI","drawId":0,"at":""},{"t":"pen","d":[162,164,164,167,168,172,177,193],"c":"rgba(0,0,0,1)","th":4,"username":"cGV0ZXI","drawId":0,"at":""},{"t":"pen","d":[164,167,168,172,177,193,184,208],"c":"rgba(0,0,0,1)","th":4,"username":"cGV0ZXI","drawId":0,"at":""},{"t":"pen","d":[168,172,177,193,184,208,193,227],"c":"rgba(0,0,0,1)","th":4,"username":"cGV0ZXI","drawId":0,"at":""},{"t":"pen","d":[177,193,184,208,193,227,208,257],"c":"rgba(0,0,0,1)","th":4,"username":"cGV0ZXI","drawId":0,"at":""},{"t":"pen","d":[184,208,193,227,208,257,217,273],"c":"rgba(0,0,0,1)","th":4,"username":"cGV0ZXI","drawId":0,"at":""},{"t":"pen","d":[193,227,208,257,217,273,232,298],"c":"rgba(0,0,0,1)","th":4,"username":"cGV0ZXI","drawId":0,"at":""},{"t":"pen","d":[208,257,217,273,232,298,238,308],"c":"rgba(0,0,0,1)","th":4,"username":"cGV0ZXI","drawId":0,"at":""},{"t":"pen","d":[217,273,232,298,238,308,249,327],"c":"rgba(0,0,0,1)","th":4,"username":"cGV0ZXI","drawId":0,"at":""},{"t":"pen","d":[232,298,238,308,249,327,251,331],"c":"rgba(0,0,0,1)","th":4,"username":"cGV0ZXI","drawId":0,"at":""},{"t":"pen","d":[238,308,249,327,251,331,252,331],"c":"rgba(0,0,0,1)","th":4,"username":"cGV0ZXI","drawId":0,"at":""},{"t":"pen","d":[249,327,251,331,252,331,252,331],"c":"rgba(0,0,0,1)","th":4,"username":"cGV0ZXI","drawId":0,"at":""},{"t":"pen","d":[251,331,252,331,252,331,252,331],"c":"rgba(0,0,0,1)","th":4,"username":"cGV0ZXI","drawId":0,"at":""},{"t":"pen","d":[252,331,252,331,252,331,252,331],"c":"rgba(0,0,0,1)","th":4,"username":"cGV0ZXI","drawId":0,"at":""},{"t":"pen","d":[252,331,252,331,252,331,252,330],"c":"rgba(0,0,0,1)","th":4,"username":"cGV0ZXI","drawId":0,"at":""},{"t":"pen","d":[252,331,252,331,252,330,252,330],"c":"rgba(0,0,0,1)","th":4,"username":"cGV0ZXI","drawId":0,"at":""},{"t":"pen","d":[252,331,252,330,252,330,253,325],"c":"rgba(0,0,0,1)","th":4,"username":"cGV0ZXI","drawId":0,"at":""},{"t":"pen","d":[252,330,252,330,253,325,253,320],"c":"rgba(0,0,0,1)","th":4,"username":"cGV0ZXI","drawId":0,"at":""},{"t":"pen","d":[252,330,253,325,253,320,254,299],"c":"rgba(0,0,0,1)","th":4,"username":"cGV0ZXI","drawId":0,"at":""},{"t":"pen","d":[253,325,253,320,254,299,253,284],"c":"rgba(0,0,0,1)","th":4,"username":"cGV0ZXI","drawId":0,"at":""},{"t":"pen","d":[253,320,254,299,253,284,250,255.99999999999997],"c":"rgba(0,0,0,1)","th":4,"username":"cGV0ZXI","drawId":0,"at":""},{"t":"pen","d":[254,299,253,284,250,255.99999999999997,247,239],"c":"rgba(0,0,0,1)","th":4,"username":"cGV0ZXI","drawId":0,"at":""},{"t":"pen","d":[253,284,250,255.99999999999997,247,239,240,209],"c":"rgba(0,0,0,1)","th":4,"username":"cGV0ZXI","drawId":0,"at":""},{"t":"pen","d":[250,255.99999999999997,247,239,240,209,237,195],"c":"rgba(0,0,0,1)","th":4,"username":"cGV0ZXI","drawId":0,"at":""},{"t":"pen","d":[247,239,240,209,237,195,232,176],"c":"rgba(0,0,0,1)","th":4,"username":"cGV0ZXI","drawId":0,"at":""},{"t":"pen","d":[240,209,237,195,232,176,230,169],"c":"rgba(0,0,0,1)","th":4,"username":"cGV0ZXI","drawId":0,"at":""},{"t":"pen","d":[237,195,232,176,230,169,226,156],"c":"rgba(0,0,0,1)","th":4,"username":"cGV0ZXI","drawId":0,"at":""},{"t":"pen","d":[232,176,230,169,226,156,225,151],"c":"rgba(0,0,0,1)","th":4,"username":"cGV0ZXI","drawId":0,"at":""},{"t":"pen","d":[230,169,226,156,225,151,224,146],"c":"rgba(0,0,0,1)","th":4,"username":"cGV0ZXI","drawId":0,"at":""},{"t":"pen","d":[226,156,225,151,224,146,224,141],"c":"rgba(0,0,0,1)","th":4,"username":"cGV0ZXI","drawId":0,"at":""},{"t":"pen","d":[225,151,224,146,224,141,224,138],"c":"rgba(0,0,0,1)","th":4,"username":"cGV0ZXI","drawId":0,"at":""},{"t":"pen","d":[224,146,224,141,224,138,224,137],"c":"rgba(0,0,0,1)","th":4,"username":"cGV0ZXI","drawId":0,"at":""},{"t":"pen","d":[224,141,224,138,224,137,224,136],"c":"rgba(0,0,0,1)","th":4,"username":"cGV0ZXI","drawId":0,"at":""},{"t":"pen","d":[224,138,224,137,224,136,224,135],"c":"rgba(0,0,0,1)","th":4,"username":"cGV0ZXI","drawId":0,"at":""},{"t":"pen","d":[224,137,224,136,224,135,224,134],"c":"rgba(0,0,0,1)","th":4,"username":"cGV0ZXI","drawId":0,"at":""},{"t":"pen","d":[224,136,224,135,224,134,224,134],"c":"rgba(0,0,0,1)","th":4,"username":"cGV0ZXI","drawId":0,"at":""},{"t":"pen","d":[224,135,224,134,224,134,224,135],"c":"rgba(0,0,0,1)","th":4,"username":"cGV0ZXI","drawId":0,"at":""},{"t":"pen","d":[224,134,224,134,224,135,224,135],"c":"rgba(0,0,0,1)","th":4,"username":"cGV0ZXI","drawId":0,"at":""},{"t":"pen","d":[297,245,297,245,297,245,298,246],"c":"rgba(0,0,0,1)","th":4,"username":"cGV0ZXI","drawId":1,"at":""},{"t":"pen","d":[297,245,297,245,298,246,300,254],"c":"rgba(0,0,0,1)","th":4,"username":"cGV0ZXI","drawId":1,"at":""},{"t":"pen","d":[297,245,298,246,300,254,303,261],"c":"rgba(0,0,0,1)","th":4,"username":"cGV0ZXI","drawId":1,"at":""},{"t":"pen","d":[298,246,300,254,303,261,313,292],"c":"rgba(0,0,0,1)","th":4,"username":"cGV0ZXI","drawId":1,"at":""},{"t":"pen","d":[300,254,303,261,313,292,318,307],"c":"rgba(0,0,0,1)","th":4,"username":"cGV0ZXI","drawId":1,"at":""},{"t":"pen","d":[303,261,313,292,318,307,327,334],"c":"rgba(0,0,0,1)","th":4,"username":"cGV0ZXI","drawId":1,"at":""},{"t":"pen","d":[313,292,318,307,327,334,331,343],"c":"rgba(0,0,0,1)","th":4,"username":"cGV0ZXI","drawId":1,"at":""},{"t":"pen","d":[318,307,327,334,331,343,334,350],"c":"rgba(0,0,0,1)","th":4,"username":"cGV0ZXI","drawId":1,"at":""},{"t":"pen","d":[327,334,331,343,334,350,335,351],"c":"rgba(0,0,0,1)","th":4,"username":"cGV0ZXI","drawId":1,"at":""},{"t":"pen","d":[331,343,334,350,335,351,335,351],"c":"rgba(0,0,0,1)","th":4,"username":"cGV0ZXI","drawId":1,"at":""},{"t":"pen","d":[334,350,335,351,335,351,335,351],"c":"rgba(0,0,0,1)","th":4,"username":"cGV0ZXI","drawId":1,"at":""},{"t":"pen","d":[335,351,335,351,335,351,336,349],"c":"rgba(0,0,0,1)","th":4,"username":"cGV0ZXI","drawId":1,"at":""},{"t":"pen","d":[335,351,335,351,336,349,335,344],"c":"rgba(0,0,0,1)","th":4,"username":"cGV0ZXI","drawId":1,"at":""},{"t":"pen","d":[335,351,336,349,335,344,334,340],"c":"rgba(0,0,0,1)","th":4,"username":"cGV0ZXI","drawId":1,"at":""},{"t":"pen","d":[336,349,335,344,334,340,334,340],"c":"rgba(0,0,0,1)","th":4,"username":"cGV0ZXI","drawId":1,"at":""},{"t":"pen","d":[348,245,348,245,348,245,348,244],"c":"rgba(0,0,0,1)","th":4,"username":"cGV0ZXI","drawId":2,"at":""},{"t":"pen","d":[348,245,348,245,348,244,349,244],"c":"rgba(0,0,0,1)","th":4,"username":"cGV0ZXI","drawId":2,"at":""},{"t":"pen","d":[348,245,348,244,349,244,349,245],"c":"rgba(0,0,0,1)","th":4,"username":"cGV0ZXI","drawId":2,"at":""},{"t":"pen","d":[348,244,349,244,349,245,350,251],"c":"rgba(0,0,0,1)","th":4,"username":"cGV0ZXI","drawId":2,"at":""},{"t":"pen","d":[349,244,349,245,350,251,351,257],"c":"rgba(0,0,0,1)","th":4,"username":"cGV0ZXI","drawId":2,"at":""},{"t":"pen","d":[349,245,350,251,351,257,358,287],"c":"rgba(0,0,0,1)","th":4,"username":"cGV0ZXI","drawId":2,"at":""},{"t":"pen","d":[350,251,351,257,358,287,363,308],"c":"rgba(0,0,0,1)","th":4,"username":"cGV0ZXI","drawId":2,"at":""},{"t":"pen","d":[351,257,358,287,363,308,378,351],"c":"rgba(0,0,0,1)","th":4,"username":"cGV0ZXI","drawId":2,"at":""},{"t":"pen","d":[358,287,363,308,378,351,387,367],"c":"rgba(0,0,0,1)","th":4,"username":"cGV0ZXI","drawId":2,"at":""},{"t":"pen","d":[363,308,378,351,387,367,399,387],"c":"rgba(0,0,0,1)","th":4,"username":"cGV0ZXI","drawId":2,"at":""},{"t":"pen","d":[378,351,387,367,399,387,404,394],"c":"rgba(0,0,0,1)","th":4,"username":"cGV0ZXI","drawId":2,"at":""},{"t":"pen","d":[387,367,399,387,404,394,407,398],"c":"rgba(0,0,0,1)","th":4,"username":"cGV0ZXI","drawId":2,"at":""},{"t":"pen","d":[399,387,404,394,407,398,407,399],"c":"rgba(0,0,0,1)","th":4,"username":"cGV0ZXI","drawId":2,"at":""},{"t":"pen","d":[404,394,407,398,407,399,407,398],"c":"rgba(0,0,0,1)","th":4,"username":"cGV0ZXI","drawId":2,"at":""},{"t":"pen","d":[407,398,407,399,407,398,407,397],"c":"rgba(0,0,0,1)","th":4,"username":"cGV0ZXI","drawId":2,"at":""}]